clarity_cli/__init__.py
clarity_cli/commands.py
clarity_cli/defs.py
clarity_cli/exceptions.py
clarity_cli/helpers.py
clarity_cli/input.py
clarity_cli/main.py
clarity_cli/outputs.py
clarity_cli-1.0.11.dist-info/METADATA
clarity_cli-1.0.11.dist-info/WHEEL
clarity_cli-1.0.11.dist-info/entry_points.txt
clarity_cli-1.0.11.dist-info/RECORD
