Metadata-Version: 2.3
Name: clarity-cli
Version: 1.0.11
Summary: Interactive CLI for test management and execution
License: MIT
Author: Clarity Team
Requires-Python: >=3.10,<4.0
Classifier: License :: OSI Approved :: MIT License
Classifier: Programming Language :: Python :: 3
Classifier: Programming Language :: Python :: 3.10
Classifier: Programming Language :: Python :: 3.11
Classifier: Programming Language :: Python :: 3.12
Classifier: Programming Language :: Python :: 3.13
Requires-Dist: click (>=8.1.3,<9.0.0)
Requires-Dist: inquirer (>=3.1.3,<4.0.0)
Requires-Dist: packaging (>=23.2,<24.0)
Requires-Dist: pydantic (>=2.11.4,<3.0.0)
Requires-Dist: pyjwt (>=2.6.0,<3.0.0)
Requires-Dist: requests (>=2.32.3,<3.0.0)
Requires-Dist: rich (>=13.3.5,<14.0.0)
Requires-Dist: tomli (>=2.0.1,<3.0.0)
Requires-Dist: tomli_w (>=1.0.0,<2.0.0)
